nickineering_ruff_config/__init__.py
nickineering_ruff_config/nickineering-ruff-base.toml
nickineering_ruff_config/update.py
nickineering_ruff_config-2.0.1.dist-info/METADATA
nickineering_ruff_config-2.0.1.dist-info/WHEEL
nickineering_ruff_config-2.0.1.dist-info/licenses/LICENSE
nickineering_ruff_config-2.0.1.dist-info/RECORD
