Metadata-Version: 2.4
Name: nickineering-ruff-config
Version: 2.0.1
Summary: A shareable Ruff starting config designed to get as much as possibly from Ruff quickly.
Project-URL: Repository, https://github.com/nickineering/ruff-config.git
Author-email: Nicholas Ferrara <git@nicholasferrara.net>
License-Expression: MIT
License-File: LICENSE
Keywords: config,configuration,dotfiles,formatting,linting,ruff,templates
Classifier: Development Status :: 4 - Beta
Classifier: Intended Audience :: Developers
Classifier: License :: OSI Approved :: MIT License
Requires-Python: ~=3.7
